{
  "project_info": {
    "project_number": "13736117814",
    "project_id": "finance-app-382403",
    "storage_bucket": "finance-app-382403.firebasestorage.app"
  },
  "client": [
    {
      "client_info": {
        "mobilesdk_app_id": "1:13736117814:android:0d403dde53b82837faba97",
        "android_client_info": {
          "package_name": "com.viictrp.financeapp"
        }
      },
      "oauth_client": [
        {
          "client_id": "13736117814-3v0d8tvlff21kavkvat58ol2n372g05h.apps.googleusercontent.com",
          "client_type": 3
        }
      ],
      "api_key": [
        {
          "current_key": "AIzaSyC0fWH3W6etB8vPZEwrhdUxFB1mILp3Nlc"
        }
      ],
      "services": {
        "appinvite_service": {
          "other_platform_oauth_client": [
            {
              "client_id": "13736117814-3v0d8tvlff21kavkvat58ol2n372g05h.apps.googleusercontent.com",
              "client_type": 3
            }
          ]
        }
      }
    }
  ],
  "configuration_version": "1"
}